README.md
pyproject.toml
setup.cfg
setup.py
spacestudio_orbit_propagation/__init__.py
spacestudio_orbit_propagation/api_client.py
spacestudio_orbit_propagation/api_response.py
spacestudio_orbit_propagation/configuration.py
spacestudio_orbit_propagation/exceptions.py
spacestudio_orbit_propagation/py.typed
spacestudio_orbit_propagation/rest.py
spacestudio_orbit_propagation.egg-info/PKG-INFO
spacestudio_orbit_propagation.egg-info/SOURCES.txt
spacestudio_orbit_propagation.egg-info/dependency_links.txt
spacestudio_orbit_propagation.egg-info/requires.txt
spacestudio_orbit_propagation.egg-info/top_level.txt
spacestudio_orbit_propagation/api/__init__.py
spacestudio_orbit_propagation/api/default_api.py
spacestudio_orbit_propagation/models/__init__.py
spacestudio_orbit_propagation/models/advanced_orbit_parameters.py
spacestudio_orbit_propagation/models/atmospheric_model.py
spacestudio_orbit_propagation/models/axis.py
spacestudio_orbit_propagation/models/body_solar_array.py
spacestudio_orbit_propagation/models/box_spacecraft_geometry.py
spacestudio_orbit_propagation/models/cartesian_ephemerides.py
spacestudio_orbit_propagation/models/circular_altitude_orbit_parameters.py
spacestudio_orbit_propagation/models/circular_ground_track_repeated_orbit_parameters.py
spacestudio_orbit_propagation/models/deployable_fixed_solar_array.py
spacestudio_orbit_propagation/models/deployable_rotating_solar_array.py
spacestudio_orbit_propagation/models/drag_perturbation.py
spacestudio_orbit_propagation/models/earth_potential_perturbation.py
spacestudio_orbit_propagation/models/elliptical_ground_track_repeated_eccentricity_orbit_parameters.py
spacestudio_orbit_propagation/models/elliptical_perigee_alt_apogee_alt_orbit_parameters.py
spacestudio_orbit_propagation/models/elliptical_perigee_alt_eccentricity_orbit_parameters.py
spacestudio_orbit_propagation/models/elliptical_sma_eccentricity_orbit_parameters.py
spacestudio_orbit_propagation/models/ephemeris_type.py
spacestudio_orbit_propagation/models/harris_priester_atmospheric_model.py
spacestudio_orbit_propagation/models/keplerian_ephemerides.py
spacestudio_orbit_propagation/models/mean_or_osculating_spacecraft_states.py
spacestudio_orbit_propagation/models/mean_or_osculating_spacecraft_states_attitude.py
