Metadata-Version: 2.1
Name: spacestudio-orbit-propagation
Version: 1.4.1
Summary: Spacestudio Orbit Propagation API
Home-page: 
Author: OpenAPI Generator community
Author-email: team@openapitools.org
License: Exotrail
Keywords: OpenAPI,OpenAPI-Generator,Spacestudio Orbit Propagation API
Requires-Dist: urllib3<2.1.0,>=1.25.3
Requires-Dist: python-dateutil
Requires-Dist: pydantic>=2
Requires-Dist: typing-extensions>=4.7.1
